{
  "home": {
    "takeTurn": "TAKE TURN",
    "playNow": "NEW GAME",
    "createGame": "Custom Game",
    "joinGame": "Lobbies",
    "myGames": "My Games",
    "startPlaying": "Start Playing Now!",
    "ranked": {
      "title": "Ranked",
      "comingSoon": "COMING SOON",
      "playMore": "Play more games"
    },
    "goGold": "GO GOLD!",
    "globalStats": {
      "gamesInProgress": "GAMES IN PROGRESS",
      "users": "USERS",
      "movesMade": "MOVES MADE"
    },
    "liveChat": {
      "title": "LIVE CHAT",
      "onlinePlayers": "{} online players",
      "online": "Online",
      "verifyEmail": "Confirm your email address to be able to chat",
      "limits": {
        "fiveMessagesPerMinute": "You can send only 5 messages per minutes"
      }
    },
    "notifications": {
      "title": "Notifications",
      "noNotifications": "No notifications yet",
      "clearAll": "Clear All",
      "gameFinished": "Game Finished",
      "positions": {
        "first": "ST",
        "second": "ND",
        "third": "RD",
        "other": "TH"
      },
      "invited": "invited you"
    },
    "buttons": {
      "awards": "AWARDS",
      "help": "HELP",
      "maps": "MAPS",
      "settings": "SETTINGS",
      "style": "STYLE"
    }
  },
  "privacy": {
    "title": "Privacy and GDPR",
    "paragraphs": {
      "1": "GDPR and The Right to be Forgotten. How can I view or delete my account data?\n",
      "2": {
        "first": "You can view all the account data that Landover stores by signing in on the app or website (",
        "second": "), and going to your profile and edit info pages.\n"
      },
      "3": "This data consists of personal info that you entered on your settings page, for example, your user IDs, username, and email, as well as mobile device info (stored so we can send notifications to your device), about info, location country and hometown that you voluntarily provided.\n",
      "4": "If you wish to completely delete your account and all data, you can choose to delete your account on the edit info / settings page.\n",
      "5": "Please be aware that deleting your account in this way will permanently remove your data, except for the data that we need to keep to exercise our legal rights or to comply with a legal obligation. For example, if you have been banned from Landover, we keep the minimum necessary information to make sure we enforce our policies and prevent future violations.\n",
      "6": "Please also note that this will not delete your game records, your comments or other public posts.\n",
      "7": "This can not be undone, even by staff, so please think carefully before deleting your account in this way.\n",
      "8": {
        "first": "***If you have lost access to your account, or have any questions about this process, please write to ",
        "second": " and we will be happy to help."
      }
    }
  },
  "playNow": {
    "unlock": "Play more casual games to unlock Ranked!"
  },
  "update": {
    "title": "Update available!",
    "web": {
      "label": "Please click bellow to clear web browser cache and get the latest update",
      "button": "Clear cache"
    },
    "mobile": {
      "label": "Please click bellow to download the latest update.",
      "button": "Update"
    },
    "androidSuffix": "\nIf the update does not appear please clear Play Store's cache"
  },
  "noConnection": {
    "title": "Connection error",
    "message": "Unable to connect with the server.\nCheck your internet connection and try again",
    "action": "Try again"
  },
  "avatar": {
    "save": "Save Changes",
    "uploadPhoto": "Upload Photo"
  },
  "achievements": {
    "title": "ACHIEVEMENTS",
    "earned": "Earned Achievement: {}",
    "openEarned": "OPEN"
  },
  "watchLiveGames": {
    "title": "Watch Live Games",
    "emptyList": "There are no active games",
    "gameLabel": "Live",
    "button": "WATCH\nLIVE GAMES"
  },
  "errors": {
    "gameAlreadyStarted": "Game already started",
    "gameDoesNotExist": "Your game doesn't exist anymore.",
    "generic": "Something went wrong. Try again.",
    "genericBig": "Something went wrong, a report has been sent to our team.",
    "uhOh": "Uh Oh",
    "error": "Error",
    "tryAgain": "Try again",
    "home": "Home",
    "login": {
      "google": {
        "failed": "Unable to sign into your google account. Please try again",
        "popupBlocked": "You have a popup blocker or ad blocker. Please allow popups and try again.",
        "popupClosed": "You didn't finish Google Sign in. Please try again.",
        "cookiesDisabled": "Please enable cookies and allow popups to continue."
      },
      "email": {
        "wrongPassword": "That password isn't right. Please try again.",
        "alreadyExists": "This email already exists as a Google or Apple login. Login with Google or Apple.",
        "notExist": "We cannot find an account associated with that email address. Please try again.",
        "wrongCode": "Code is wrong",
        "failedToLink": "Failed to link credentials, try again",
        "badFormat": "Invalid email format.",
        "notAssociated": "No user was found with that email address.",
        "generatingVerifyLinkFailed": "Error generating email link"
      },
      "facebook": {
        "failed": "Unable to sign into your facebook account. Please try again"
      },
      "generic": "{} Please try again"
    }
  },
  "game": {
    "logs": {
      "tooltip": "Live log",
      "noLogs": "No Logs",
      "military": {
        "upgraded": "upgraded",
        "military": "military"
      },
      "tokens": {
        "islandExploredSuffix": "explored a new island. Earned 1 VP!",
        "longestTrailSuffix": "got longest road ({}). Earned 2 VP!",
        "portAuthoritySuffix": "got Port Authority. Earned 2 VP!"
      },
      "started": {
        "prefix": "New",
        "suffix": "player game started on"
      },
      "raid": {
        "raided": "raided",
        "freeRaided": "free raided"
      },
      "trade": {
        "traded": "traded",
        "for": "for"
      },
      "catapult": {
        "catapult": "catapult",
        "removed": "spent one military to remove",
        "allRemoved": "All Catapults have been removed from the board."
      },
      "devCards": {
        "drawn": "drew a development card"
      },
      "resources": {
        "received": "Received",
        "discarded": "discarded",
        "earned": "earned",
        "aqueductSuffix": "from aqueduct"
      },
      "charity": {
        "charity": "Charity!",
        "earnedPrefix": "Everyone but",
        "earnedSuffix": "earned",
        "everyoneEarned": "Everyone earned"
      },
      "barbarian": {
        "attack": "Barbarian attack",
        "failed": "The players failed to defend the",
        "lostCity": "lost a city.",
        "defended": "successfully defended",
        "earnedVP": "earned VP with highest military",
        "earnedCardSuffix": "rewarded a development card."
      },
      "culture": {
        "upgradedPrefix": "upgraded",
        "upgradedSuffix": "culture"
      },
      "bonusTime": "received {} turn timer bonus",
      "gameOver": "Game Over",
      "you": "You",
      "your": "Your",
      "were": "were",
      "was": "was",
      "turn": "Turn",
      "rolled": "rolled",
      "built": "built a",
      "stole": {
        "one": "Stole from {} player",
        "many": "Stole from {} players",
        "other": "Stole from {} players",
        "failed": "Couldn't steal resources."
      }
    },
    "devCards": {
      "title": "played {} card.",
      "newDevCard": "New dev card: {}",
      "subtitle": {
        "masterMerchant": {
          "oneCard": "Took one card from {}",
          "twoCards": "Took two cards from {}"
        },
        "merchant": {
          "withVP": "on {}, earned 1 VP.",
          "withoutVP": "on {}."
        },
        "merchantFleet": {
          "oneResource": "Can now trade {} 2:1 this turn",
          "allResources": "Can now trade {} 2:1"
        },
        "commercialHarbor": "Traded 1 resource for 1 commodity",
        "resourceMonopoly": {
          "oneWithoutResources": "Stole resources from {}",
          "moreWithoutResources": "Stole resources from {} players",
          "failed": "Tried to steal some resources but got nothing",
          "failedWithResource": "Tried to steal {} but got nothing",
          "withResourcesAllSame": "Stole {} {} from {}",
          "withResourcesDifferent": "Stole 2 {} from {} and 1 $resourceName from {}"
        },
        "commodityMonopoly": {
          "oneVictim": "Stole commodities from {}",
          "moreVictims": "Stole commodities from {} players",
          "failed": "Tried to steal some commodities but got nothing"
        },
        "expedition": "Converted tile to gold",
        "famine": "{} discarded random cards",
        "plenty": {
          "withoutResources": "Got 2 resources",
          "withResources": "Got 2 resources: {}"
        },
        "excavation": "Received two clays for each building on a clay tile",
        "forestry": "Received two wood for each building on a wood tile",
        "irrigation": "Received two wheat for each building on a wheat tile",
        "mining": "Received two ore for each building on an ore tile",
        "borderCollie": "Received two sheep for each building on a sheep tile",
        "inventor": "Swapped two number tiles",
        "medicine": "Built a city for 2 ore and 1 wheat",
        "roadBuilding": "Built two roads/bridges",
        "military": "Upgraded military",
        "crane": "Reduced culture upgrade cost",
        "siege": {
          "oneVictim": "Stole resources from {}",
          "moreVictims": "Stole resources from {} players"
        },
        "bishop": "Removed catapult",
        "deserter": "Stole military from {}",
        "vandal": "Destroyed {}'s bridge/road",
        "diplomat": "Moved one trail",
        "raze": "Destroyed {}'s city",
        "spy": "Stole dev card from {}",
        "wedding": {
          "oneVictim": "Stole cards from {}",
          "moreVictims": "Stole cards from {} players"
        },
        "anarchy": "Randomized number tiles",
        "alchemist": "Chose dice roll numbers",
        "traitor": "Advanced the barbarians tracker"
      },
      "masterMerchant": {
        "title": "Master Merchant",
        "description": "Pick any player with more victory points, see their hand and pick two resource or commodity cards.",
        "cannotPlay": "There are no players that have more victory points than you",
        "dialog": {
          "title": "Steal!"
        }
      },
      "merchant": {
        "title": "Merchant",
        "description": "Move the merchant token to your own settlement or city. The player that possesses the merchant may trade that resource 2:1 with the bank. Worth 1 VP.",
        "dialog": {
          "title": "Place Merchant",
          "message": "Are you sure you want to place a merchant here?",
          "yes": "Yup!",
          "no": "Cancel"
        }
      },
      "merchantFleet": {
        "title": "Merchant Fleet",
        "description": "Pick one resource or commodity of your choice to trade with the bank at a 2:1 rate for this turn only."
      },
      "commercialHarbor": {
        "title": "Commercial Harbor",
        "description": "Trade 1 resource for 1 commodity."
      },
      "resourceMonopoly": {
        "title": "Resource Monopoly",
        "description": "Pick a resource. Each player must give you (up to) two of those resources if they have it."
      },
      "commodityMonopoly": {
        "title": "Commodity Monopoly",
        "description": "Pick a commodity. Each player must give you one of that commodity if they have it."
      },
      "expedition": {
        "title": "Expedition",
        "description": "Choose any tile on the board and convert it to a gold resource tile.",
        "dialog": {
          "title": "Are you sure",
          "message": "Do you want to turn this tile into gold?",
          "no": "No",
          "yes": "Yes"
        }
      },
      "famine": {
        "title": "Famine",
        "description": "All players with more VPs than you discard 2 random resources.",
        "cannotPlay": "There are no players with more victory points than you."
      },
      "plenty": {
        "title": "Plenty",
        "description": "Get two resources of your choice."
      },
      "excavation": {
        "title": "Excavation",
        "description": "Receive 2 clay per settlement on each clay tile"
      },
      "forestry": {
        "title": "Forestry",
        "description": "Receive 2 wood per settlement on each wood tile"
      },
      "irrigation": {
        "title": "Irrigation",
        "description": "Receive 2 wheat per settlement on each wheat tile"
      },
      "mining": {
        "title": "Mining",
        "description": "Receive 2 ore per settlement on each ore tile"
      },
      "borderCollie": {
        "title": "Border Collie",
        "description": "Receive 2 sheep per settlement on each sheep tile"
      },
      "inventor": {
        "title": "Inventor",
        "description": "Swap two number tiles on the board. Swappable numbers are: 3, 4, 5, 9, 10, and 11.",
        "tileSelected": "Swap these tiles?",
        "dialog": {
          "title": "Swap Tiles",
          "message": "Do you want swap the values of these two tiles?",
          "yes": "Yes",
          "no": "Cancel"
        }
      },
      "medicine": {
        "title": "Medicine",
        "description": "Build a city for 2 ore and 1 wheat.",
        "cannotAfford": "You need to have at least two ore and one wheat to use this card",
        "cannotPlace": "There is no where on the board to place a city",
        "upgradeTitle": "Build {} with {}"
      },
      "roadBuilding": {
        "title": "Road Building",
        "description": "Place two roads or two bridges, or one of each, at no cost to you."
      },
      "military": {
        "title": "Military",
        "description": "Upgrade your military power by one level.",
        "cannotPlay": "You are already have the maximum military power."
      },
      "crane": {
        "title": "Crane",
        "description": "After playing this card, your next culture improvement this turn costs one fewer commodity",
        "cannotPlay": "You cannot play this card because you have no cities or you have a Crane Card already in play."
      },
      "siege": {
        "title": "Siege",
        "description": "Carry out a raid but steal one random resource from every player who has a village or city on the raided tile. Does not cost a military point"
      },
      "bishop": {
        "title": "Bishop",
        "description": "Remove a catapult from the board.",
        "cannotPlay": "There are no catapults on the board for you to remove."
      },
      "deserter": {
        "title": "Deserter",
        "description": "Steal one level of military power from a player of your choice.",
        "cannotPlayMaxedPower": "Your military has reached its max power of 3. Upgrade your politics to level 3 to increase your max.",
        "cannotPlayBarracks": "You already have max military power.",
        "cannotPlayEmpty": "No one has any military power; there is nothing to steal"
      },
      "vandal": {
        "title": "Vandal",
        "description": "Remove another player's road or bridge of your choosing."
      },
      "diplomat": {
        "title": "Diplomat",
        "description": "Move one of your own roads or bridges to a new location.",
        "cannotPlay": "You have no trails to move."
      },
      "raze": {
        "title": "Raze",
        "description": "Lose 1 military power and destroy a non walled city of any player with more VPs than you. You must have military power greater than or equal to 1 to play this card.",
        "cannotPlayNoPlayers": "There are no players with more victory points than you",
        "cannotPlayNoBuildings": "There are no buildings to destroy",
        "cannotPlayNoMilitary": "You must have at least one military power to use this card",
        "dialog": {
          "title": "Are you sure?",
          "message": "Do you want to destroy this city?",
          "yes": "Yes!",
          "no": "No"
        }
      },
      "spy": {
        "title": "Spy",
        "description": "Pick a player, see their dev cards and choose one to steal.",
        "cannotPlay": "No other player currently has development cards.",
        "dialog": {
          "title": "Steal!"
        }
      },
      "wedding": {
        "title": "Wedding",
        "description": "Steal two random cards (resources or commodities) from every player that has more victory points than you.",
        "cannotPlay": "There are no players with more victory points than you."
      },
      "anarchy": {
        "title": "Anarchy",
        "description": "Randomize all the number tiles on the board until a 7 is rolled."
      },
      "alchemist": {
        "title": "Alchemist",
        "description": "Each turn you possess this card, you have the option of choosing the exact numbers on both 6-sided dice or doing a normal random roll.",
        "cannotPlay": "This development card is only playable at the beginning of the turn."
      },
      "traitor": {
        "title": "Traitor",
        "description": "Advance the barbarian 2 spots. Will stop just before an attack."
      },
      "constitution": {
        "title": "Constitution",
        "description": "1 Victory Point. Played immediately and does not count towards your max 5 dev cards."
      },
      "printer": {
        "title": "Printer",
        "description": "1 Victory Point. Played immediately and does not count towards your max 5 dev cards."
      }
    },
    "chat": {
      "loadingError": "Something went wrong, please try again",
      "noMessages": "No messages yet",
      "emptyMsg": "Your message is empty. Please enter some text.",
      "addMsgHint": "Add message",
      "yourMsg": "you",
      "banned": "You are chat restricted until {}. Please be respectful when chatting to avoid future bans. We want to keep this community fun for everyone!",
      "profanityDetected": "Profanity detected. Try again.",
      "banConfirmation": {
        "title": "Ban Player",
        "message": "Are you sure you want to ban this player from chat? You won't see any messages from them",
        "yes": "Yes",
        "no": "No",
        "failed": "Something went wrong, please try again"
      },
      "unMuteConfirmation": {
        "title": "Unmute Player",
        "message": "Are you sure you want to unmute this player?"
      },
      "chatActionType": {
        "joinGame": "{} has join the game",
        "leftGame": "{} has left the game",
        "invitePlayer": "{} invited {} to the game",
        "botAdded": "{} added a bot",
        "botRemoved": "{} removed a bot"
      }
    },
    "playerTurnOverlay": {
      "playerNameSuffix": "'s",
      "playerTurn": "turn"
    },
    "buildDialog": {
      "title": "BUILD",
      "trade": "Trade",
      "cannotAfford": "You can't afford that!",
      "structureRequires": "{} requires:",
      "cannotBuild": "Cannot build {}",
      "cannotBuildReason": "You have nowhere to put it."
    },
    "trailTypeDialog": {
      "title": "CHOOSE ONE",
      "subtitle": "What would you like to build?",
      "cannotAfford": "You can't afford that!",
      "trailsRequires": "{} requires:"
    },
    "devCardsDialog": {
      "title": "DEV CARDS",
      "defaultButton": "Play Card",
      "noCards": "No Development Cards",
      "cannotPlay": "Can't Play {} Card"
    },
    "playerModalDialog": {
      "military": "Military",
      "militaryUpgrade": "Upgrade",
      "militaryRequires": "Upgrading your military requires",
      "militaryCannotAfford": "You can't afford that!",
      "raid": "Raid",
      "culture": "Culture",
      "cultureUpgrade": "Upgrade",
      "devCards": "Dev Cards",
      "devCardsPlay": "Play",
      "build": "Build",
      "trade": "Trade",
      "raidError": {
        "title": "Unable to raid",
        "message": "You cannot raid right now"
      },
      "points": {
        "victoryPoints": "Victory Points",
        "longestRoute": "Longest Route",
        "military": "Military",
        "islands": "Islands Explored",
        "devCards": "Dev Cards",
        "merchant": "Merchant Tokens",
        "ports": "Port Authority"
      }
    },
    "safeRollDialog": {
      "title": "SAFE ROLL?",
      "message": "You're at risk of discarding half of your hand!",
      "riskyRoll": "Risky Roll",
      "safeRoll": "Safe Roll"
    },
    "safeTokens": {
      "title": "BUY SAFE TOKENS"
    },
    "rollType": {
      "description": "Roll dice or use your Alchemist card to choose your numbers",
      "alchemist": "Use Alchemist",
      "random": "Random Roll"
    },
    "gameOver": {
      "title": "Game Over",
      "stats": "Stats",
      "home": "Home",
      "linkCopied": "Game link copied to clipboard",
      "goGold": "GO GOLD!",
      "rematch": "Rematch",
      "favoriteMap": "Favorite Map",
      "unfavoriteMap": "Unfavorite Map",
      "won": "{} \nwon!",
      "upgradeToSee": "Upgrade to see \n 12 more stats!"
    },
    "players": {
      "resourceCards": "Resource Cards",
      "devCards": "Development Cards",
      "military": "Military Points",
      "scienceLevel": "Science Level",
      "commerceLevel": "Commerce Level",
      "politicsLevel": "Politics Level",
      "merchant": "Merchant Token",
      "portPoints": "Port Points",
      "longestRoad": "Longest Road",
      "victoryPoints": "Victory Points"
    },
    "rematch": {
      "canceled": {
        "title": "REMATCH",
        "close": "Close",
        "declined": "Rematch declined"
      },
      "ready": {
        "title": "GET READY!",
        "cancel": "CANCEL"
      },
      "request": {
        "title": "Rematch Requested",
        "yes": "Yes",
        "no": "No"
      },
      "reject": {
        "title": "Reject Rematch?",
        "message": "re you sure you want to reject this game?",
        "yes": "Reject"
      }
    },
    "replay": {
      "turnNumber": "Turn {} of {}",
      "replayLast": "Replay last",
      "turn": {
        "one": "turn",
        "many": "turns",
        "other": "turns"
      },
      "purchase": {
        "title": "REPLAYS",
        "description": "Replays allow you to rewatch all turns to see what happened since your last turn…or replay the whole game when it’s over!  Want to unlock full replays?",
        "no": "No thanks",
        "yes": "Go Gold"
      }
    },
    "swipeableDevCardDialog": {
      "close": "Close",
      "play": "Play Card",
      "cannotPlay": "Can't play {}",
      "wrongTurn": "It's not your turn"
    },
    "actions": {
      "raid": {
        "tileSelected": "Raid this tile?",
        "removeCatapult": "Remove this catapult?"
      },
      "metro": {
        "placeIt": "Metro! Select any of your cities to place it."
      },
      "chooseTile": {
        "bishop": "Choose catapult to remove",
        "expedition": "Choose tile to convert to gold",
        "inventor": "Choose two tiles to swap numbers",
        "merchant": "Place your merchant token",
        "siege": "Choose tile to siege",
        "raid": "Choose tile to raid"
      },
      "chooseRoads": {
        "placeRoad": "Place road or bridge",
        "place2Roads": "Place 2 roads or bridges",
        "selectRoad": "Select a road or bridge",
        "selectEnemyRoad": "Select an enemy road or bridge",
        "confirm": "Build {}?"
      },
      "chooseCorner": {
        "selectEnemyCity": "Select an enemy city",
        "placeVillage": "Place your village",
        "placeCity": "Place your city",
        "confirmVillage": "Build a village?",
        "confirmCity": "Build a city?",
        "confirmCityWall": "Build a city wall?",
        "confirmMetro": "Build a metro?"
      },
      "roll": "Roll the Dice",
      "build": "Build",
      "remove": "Remove",
      "move": "Move"
    },
    "menu": {
      "gameActions": "GAME ACTIONS",
      "info": "INFO",
      "turnReplay": "Turn Replays",
      "rollFirst": "Please roll dice first.",
      "surrender": "Surrender",
      "surrenderDialog": {
        "title": "Surrender",
        "message": "Are you sure you want to surrender?\nThere is no penalty for admitting defeat.",
        "yes": "Surrender",
        "no": "Cancel"
      },
      "share": "Share",
      "reportBug": {
        "title": "Report Bug",
        "thanks": "Thanks!",
        "message": "Thanks for submitting this bug.\nWe'll investigate and work on a fix!"
      },
      "settings": "Settings",
      "prodChart": "Prod Chart",
      "devCards": "Dev Cards",
      "rules": "Rules",
      "cancel": "Cancel"
    },
    "settings": {
      "title": "SETTINGS",
      "sound": "Sound",
      "music": "Music",
      "mapHints": "Map Hints",
      "chatNotifications": "Chat Notifications",
      "turnNotifications": "Turn Notifications",
      "autoJump": "Auto jump to next game",
      "showReplays": "Show Replays",
      "autoRoll": "Auto-Roll Dice"
    },
    "playerControls": {
      "military": "Military",
      "science": "Science",
      "commerce": "Commerce",
      "politics": "Politics"
    },
    "pickPlayer": {
      "title": "PICK PLAYER",
      "noPlayers": "No players to steal from.\nAll players have zero resources.",
      "button": "Select"
    },
    "barbarianDialogs": {
      "basic": "Barbarians",
      "barbarianLead": "Barbarians Lead",
      "playerLead": "Player Lead",
      "defense": "Total defense",
      "barbarianStrength": "Barbarian Strength",
      "attackPossibleIn": "Attack possible in {} Turns",
      "leaderboard": "Leaderboard",
      "defeat": {
        "title": "Defeat",
        "playersAffected": "{} players",
        "leastMilitary": "Least Military",
        "lostCity": {
          "one": "Lost a city",
          "many": "Each lost a city",
          "other": "Each lost a city"
        }
      },
      "upgradeMilitary": "Upgrade Military",
      "result": "BARBARIANS ATTACK",
      "won": {
        "title": "Defended",
        "playersAffected": "{} players",
        "mostMilitary": "Most Military",
        "prize": {
          "one": "+1 VP",
          "many": "+1 Dev Card each",
          "other": "+1 Dev Card each"
        }
      },
      "dataNotAvailable": "Data not available"
    },
    "stats": {
      "victoryPoints": "Victory Points",
      "villages": "Villages",
      "cities": "Cities",
      "roadsBridges": "Roads/Bridges",
      "military": "Military",
      "metros": "Metros",
      "self7Rolls": "Self 7 Rolls",
      "discards": "Discards",
      "devCards": "Dev Cards",
      "raids": "Raids",
      "raided": "Raided",
      "trades": "Trades",
      "wheat": "Wheat",
      "ore": "Ore",
      "brick": "Brick",
      "wood": "Wood",
      "sheep": "Sheep",
      "paper": "Paper",
      "cloth": "Cloth",
      "coin": "Coin"
    },
    "metroEarned": {
      "title": "Metro!",
      "msg": "Congratulations, you've earned a metro. Tap on any city to place it.",
      "ok": "Ok!"
    },
    "merchant": {
      "title": "Merchant Token",
      "msg": "The player who controls the merchant token may trade this resource 2:1."
    },
    "harbor": {
      "title": "Harbor",
      "tradeAmount2": "2 {} resources",
      "tradeAmount3": "3 resources of a single type",
      "description": "Trade $tradeAmount for 1\n other resource or commodity."
    },
    "bottomBar": {
      "confirmAction": "Yes",
      "cancelAction": "No"
    },
    "culture": {
      "title": "CULTURE",
      "upgrade": "Upgrade"
    },
    "cultureUpgrade": {
      "close": "Close",
      "achieved": "ACHIEVED!",
      "upgrade": "Upgrade {}",
      "cannotUpgrade": "Cannot upgrade",
      "noCity": "You must have an open city with no metropolis to upgrade your culture to level 4 or 5."
    },
    "devCardsInfo": {
      "title": "DEV CARDS"
    },
    "diceRolls": {
      "title": "DICE ROLLS",
      "history": "Roll History:"
    },
    "devDiscard": {
      "title": "Discard",
      "description": "You may only keep {} cards. Choose {} below to discard.",
      "cardsDiscarded": {
        "one": "a card",
        "many": "{} cards",
        "other": "{} cards"
      }
    },
    "feedback": {
      "title": "Feedback",
      "send": "Send",
      "label": "Bug find or brilliant idea?",
      "placeholder": "We love to hear from our users!",
      "emptyError": "Please enter some feedback"
    },
    "freeRaid": {
      "title": "Free Raid",
      "description": "Last place 7 roll awards you a free raid. Place your catapult to steal a resource from an opponent. ",
      "button": "Raid"
    },
    "military": {
      "title": "MILITARY",
      "maxPart1": "Max military: ",
      "maxPart2": "3 (Barracks increases to 6)",
      "raid": "Raid",
      "raidUnable": "Unable to raid",
      "cannotRaid": "You can't afford to raid",
      "raid-1": "Raid   -1",
      "militaryPower": "Your Military Power",
      "vs": "vs",
      "barbarianStrength": "Barbarian Strength",
      "totalDefense": "Total Defense",
      "upgrade": {
        "title": "Upgrade",
        "cannotAfford": "You cannot afford it!",
        "upgradeRequires": "Upgrading your military requires",
        "maxPower": "Max Military Power",
        "maxPowerDesc": "Your military has reached its max power of 3. Upgrade your politics to level 3 to increase your max.",
        "maxPowerBarracks": "Max Military Power",
        "maxPowerBarracksDesc": "Your military has reached its max power of 6. Launch raids to use your military."
      }
    },
    "newIsland": {
      "title": "ISLAND EXPLORED!",
      "description": "You´ve explored a new island!",
      "prize": "+1 Victory Point",
      "button": "OK"
    },
    "prodChart": {
      "title": "PRODUCTION CHART",
      "village": "Village",
      "city": "City"
    },
    "selectCard": {
      "button": "Confirm",
      "choose": "Choose {}"
    },
    "trade": {
      "title": "TRADE",
      "give": "GIVE",
      "receive": "RECEIVE",
      "resourcesLabel": "Your resources:",
      "emptyTrade": "Nothing to trade"
    },
    "tradeToBuild": {
      "title": "TRADE TO BUILD",
      "build": "Build {}",
      "missing": "Missing",
      "resourcesLabel": "Your resources",
      "and": "and"
    },
    "endTurn": {
      "nextGame": "Next game",
      "wait": "Wait",
      "end": "End",
      "turn": "Turn",
      "endTurn": "End Turn",
      "nothingToDo": "Looks like there’s nothing left to do.",
      "endTurnConfirm": "End Turn?",
      "canUpgrade": "Are you sure you want to end turn? You can upgrade your culture without a trade!",
      "lotOfResources": "Are you sure you want to end your turn? You have a lot of unspent resources.",
      "cancel": "Cancel"
    },
    "errors": {
      "cannotFindGame": "We can't find the game, please try again",
      "timeExpired": "Time Expired",
      "timeExpiredMsg": "You have run out of time and been removed from the game.",
      "close": "Close"
    },
    "currencies": {
      "clay": "Clay",
      "wood": "Wood",
      "wheat": "Wheat",
      "wool": "Whool",
      "ore": "Ore",
      "paper": "Paper",
      "cloth": "Cloth",
      "coin": "Coin",
      "random": "Random"
    }
  },
  "tutorial": {
    "viewProductChart": "View Product Chart Table",
    "continue": "Tap to continue",
    "coach": "Coach",
    "learningMode": {
      "title": "Welcome to Landover!",
      "description": "In this tutorial we're going to get you acquainted with the <bold>interface</bold> and the <bold>flow of the game</bold>. However, the more games you play, the better you will start to understand the strategies."
    },
    "firstVillage": {
      "title": "First Village",
      "description": "Place your village on a high value corner below. They are indicated in red. Try to get one that has 3 different types of resources. It's always good to start with wheat, clay, wood, or sheep."
    },
    "firstRoad": {
      "title": "First Road",
      "description": "Now place a road from your village towards another good corner."
    },
    "firstCity": {
      "title": "First City",
      "description": "Place your city on another high value corner below. Whatever resources you didn't get with your village, try and get those with your city. Remember cities and villages must always be separated by at least one empty corner."
    },
    "secondRoad": {
      "title": "Second Road",
      "description": "And again place a road from your city towards another good corner."
    },
    "rollTime": {
      "title": "Time to Roll",
      "description": "'Now that you have placed your initial settlements, it's time to roll the dice and start collecting resources. Keep rolling until you have enough resources to build some more stuff."
    },
    "moreRoads": {
      "title": "Build more Roads",
      "description": "It looks like you have enough resources to build more roads. Go ahead and build more roads further from your settlements."
    },
    "anotherVillage": {
      "title": "Build another Village",
      "description": "'You now have enough resources to build a village and there is an open spot waiting for you. Go ahead and build another village to expand your empire and collect more resources each turn."
    },
    "productionChart": {
      "title": "Production Chart",
      "description": "Below is how many resources villages and cities produce: "
    },
    "trading": {
      "title": "Trading",
      "description": "The Landover bank allows you to trade any resource or commodity 3 for 1. It looks like you can upgrade your village to a city but it requires a trade. Go ahead and try building a city and you should see the Trade to Build prompt. If you want more economical trades, try building a village on a harbor which gives you a 2 for 1 ability."
    },
    "culture": {
      "title": "Culture",
      "description": "Now that you have a commodity, go ahead and open up the culture modal and upgrade. Upgrading culture will give you the potential of earning valuable dev cards, unlocking new abilities, or eventually earning metros which are worth additional VPs."
    },
    "cities": {
      "title": "Cities",
      "description": "Go ahead and choose a village you'd like to upgrade to a city. It costs 3 ore and 2 wheat but will double the production of your village!"
    },
    "military": {
      "title": "Military",
      "description": "Now that your economy is moving along, it's time to build some military to ward off barbarian attacks. You need one military power for each city when barbarians attack to avoid losing a city. The barbarian tracker is top right and shows how many rolls until they attack. Go ahead…"
    },
    "barbarians": {
      "title": "Barbarians",
      "description": "Barbarians are on their way. The shield top right shows if you are safe or not. If it's red, you need more military. If it's green, then you are safe. Each time they attack you'll lose 1 military power so be sure to keep adding more military over time."
    },
    "metros": {
      "title": "Metros",
      "description": "Be sure to keep upgrading your culture with your commodity cards. Once you reach level 4 you'll receive a metro worth +2VP. Metros are immune from barbarian attacks and can't be razed by other players."
    },
    "spendResources": {
      "title": "Spend Your Resources",
      "description": "You currently are at risk of discarding half your cards if a 7 is rolled! Be sure to spend your resources or build city walls to increase your hand size. City walls cost 2 clay and can be built on any cities. "
    },
    "goodLuck": {
      "title": "Good Luck!",
      "description": "It looks like you are well on your way to 15 VPs. Keep expanding, building villages, upgrading to cities, leveling up your military, and building metros. If you have questions, join us on discord. Try some games against the bots, and when you're ready, challenge your friends!"
    },
    "end": {
      "title": "Congratulations",
      "description": "You have just reached 15 VPs and have won the game! Hopefully you had some fun along the way. We highly recommend you try a solo game against one bot."
    }
  },
  "subscription": {
    "cancel": {
      "title": "Cancel Subscription",
      "message": "Sorry to see you are not happy with your subscription. Can you please take a moment to leave some feedback for us in our Discord channel first? We're always trying to improve the app!",
      "feedbackButton": "Leave Feedback",
      "cancelButton": "Cancel Subscription"
    }
  },
  "discord": {
    "title": "JOIN THE COMMUNITY!",
    "msg1": "Woah, you're building some momentum!",
    "msg2": "Want to meet other Landover players, find games, learn about new features and talk directly with our dev team?",
    "button": "Join Discord"
  },
  "itp": {
    "titleLetsPlay": "LET'S PLAY",
    "titleSuccess": "GREAT!",
    "message": "Looks like you need some games. We have players ready and waiting!",
    "messageSuccess": {
      "one": "You are now in {} game!",
      "many": "You are now in {} games!",
      "other": "You are now in {} games!"
    },
    "myGames": "Go to My Games",
    "startGames": {
      "one": "Start {} Game",
      "many": "Start {} Games",
      "other": "Start {} Games"
    },
    "footerMessage": "No pressure! We'll just ping you when it's your turn to move.",
    "error": "We were unable to join you to the selected games"
  },
  "ongoingGame": {
    "inLobby": {
      "title": "LIVE GAME LOBBY",
      "leaveBtn": "Leave",
      "rejoinBtn": "Rejoin",
      "bottomMsg1": "You’re currently in a live game lobby!",
      "bottomMsg2": "Please leave or rejoin the game lobby so you’re ready to go once the game starts."
    },
    "inGame": {
      "title": "LIVE GAME",
      "leaveBtn": "Surrender",
      "rejoinBtn": "Rejoin",
      "bottomMsg1": "You’re currently in a live game!",
      "bottomMsg2": "Please surrender or rejoin this game so other\nplayers don’t wait on you."
    },
    "gameNotExist": "Your game doesn't exist anymore.",
    "somethingWentWrong": "Something went wrong. Try again or start a new game."
  },
  "upgradeDialog": {
    "title": "UPGRADE TO GOLD",
    "error": "Purchase error",
    "footer": {
      "comingSoon": "Coming soon...",
      "createAccount": "Create Account",
      "watchAd": "Watch Ad",
      "noAds": "Sorry, there's no ads available right now",
      "restore": "Restore Purchase",
      "noPurchase": "There is no active subscription",
      "policy": "Subscription Policy",
      "noTrial": "No trial available. Billed immediately. Subscription not required. May cancel at any time from within the app."
    }
  },
  "buildingStyles": {
    "default": "default",
    "alien": "alien",
    "modern": "modern",
    "fantasy": "fantasy",
    "toys": "toys"
  },
  "culture": {
    "science": {
      "abilityName": "Aqueduct",
      "abilityDescription": "If a player does not receive\nany resources for a given\nroll, they are given one\nrandom resource.",
      "abilityAnnouncement": "If you don't get any resources on a roll, you will now be given one random resource."
    },
    "commerce": {
      "abilityName": "Bank",
      "abilityDescription": "Allows players to trade\ncommodities 2:1 with the\nbank for any resource or\ncommodity.",
      "abilityAnnouncement": "You can now trade commodities 2:1 with the bank."
    },
    "politics": {
      "abilityName": "Barracks",
      "abilityDescription": "Military power can be\nincreased above level 3. Military power can be\nincreased above level 3.",
      "abilityAnnouncement": "Your max military power has been increased from 3 to 6."
    }
  },
  "gameStartTypes": {
    "ranked": "Ranked",
    "quick": "Quick",
    "custom": "Custom",
    "welcome": "Welcome"
  },
  "gameType": {
    "custom": "Live",
    "daily": "Daily",
    "tutorial": "Tutorial",
    "solo": "Solo",
    "private": "Private"
  },
  "premium": {
    "premiumBots": "Play with 14 Bots each with unique strengths",
    "premiumStyles": "Get access to 4 alternative themes and preferred colours",
    "premiumPlayersNumber": "Create epic 8 player games with friends",
    "premiumGameOptions": "Create custom games tailored to you",
    "premiumStats": "Analyze the game results to become better",
    "premiumAvatars": "Use any image you want as an in-game avatar",
    "premiumMaps": "Design new and exciting maps",
    "premiumNoAds": "No ADS. Directly support the developers!",
    "title": "Gold Member",
    "lastPayment": "Last Payment",
    "nextPayment": "Next Payment",
    "cancelled": "Cancelled\nEnds on:",
    "cancel": "Cancel",
    "canceledTitle": "Subscription",
    "canceledMessage": "Subscription successfully canceled",
    "success": {
      "title": "Success!",
      "home": "Home",
      "message": "You are now a gold user",
      "safeRollMsg": "Safe Roll tokens successfully purchased."
    },
    "canceled": {
      "title": "Canceled",
      "home": "Home",
      "message": "Something went wrong during checkout"
    }
  },
  "ranks": {
    "promoted": {
      "title": "PROMOTED!",
      "message": "Congratulations! \nYour amazing play has earned you a ranking level up!"
    },
    "demoted": {
      "title": "DEMOTED!",
      "message": "Oh no! You have ranked down.\nMaybe it's time to try a new strategy or pray to the dice gods?"
    },
    "viewRanks": "View Ranks",
    "title": "RANKS",
    "rules": "How rankings work",
    "globalStats": "Global Stats",
    "yourRankWrap": "YOUR\nRANK",
    "leaderboard": {
      "title": "RANKING LEADERBOARD",
      "shortTitle":"Leaderboard",
      "player": "Player",
      "games":"# Games",
      "rank": "Rank",
      "MMR": "MMR",
      "yourRank": "YOUR RANK",
      "noPlayers": "No players yet",
      "viewAll": "View All"
    }
  },
  "dailyGames": {
    "noGames": "No Games in progress",
    "startGame": "Start a Game",
    "createGame": "Create",
    "joinByCode": "Join",
    "history": "History",
    "turnCount": {
      "many": "turns",
      "single": "turn"
    },
    "gameType": {
      "ranked": "Ranked",
      "casual": "Casual"
    },
    "title": "My Games",
    "game": {
      "waiting": "Waiting...",
      "rematchRequest": "Rematch Request",
      "gameOver": "Game Over",
      "play": "Play",
      "invite": "Invite players",
      "start": "Start Game?"
    }
  },
  "profile": {
    "editInfo": "Edit info",
    "city": "City",
    "description": "Description",
    "email": "Email",
    "name": "Name",
    "status": "Status",
    "save": "Save",
    "linkCopied": "Profile link copied to clipboard",
    "emailWillBeChanged": "Email will be changed after confirmation",
    "settings": {
      "turnEmails": "Send Turn Emails",
      "chatNotifications": "Chat Notifications",
      "recentInvites": "Allow Recent Invites",
      "autoJump": "Auto-Jump to Next Daily Game",
      "mapHints": "Map Hints",
      "showReplays": "Show Replays",
      "acceptNewGames": "Auto-Accept New Games",
      "autoRoll": "Auto-Roll Dice on Turn Start",
      "effects": "Effects",
      "music": "Music",
      "off": "OFF",
      "on": "ON"
    },
    "account": {
      "signUp": "Sign Up",
      "saveAccount": "SAVE ACCOUNT",
      "emailSentTitle": "Email sent",
      "emailSentMsg": "Please check your mailbox and confirm your email address. Then you can use this account."
    },
    "history": {
      "title": "History",
      "filter": "Filter",
      "empty": "No Match History",
      "recentGames": "Recent Games",
      "viewAll": "View All"
    },
    "mapStats": {
      "title": "Map Stats",
      "filter": "Filter",
      "empty": "No Stats"
    },
    "rank": "Rank",
    "season": {
      "progress": "Season Points"
    },
    "delete": {
      "title": "Delete Account",
      "dialog": {
        "title": "Are you sure?",
        "message": "We’re sorry to see you go! Are you sure you want to delete your account? All your stats and games will be permanently removed.\nYou must confirm your account to delete it.",
        "no": "No",
        "yes": "Yes"
      },
      "enterPassword": "Enter a password",
      "enterPasswordInstruction": "Please enter a password for your account below"
    },
    "stats": {
      "filter": {
        "title": "FILTER",
        "clear": "Clear",
        "filter": "Filter"
      },
      "totalGames": "Total Games - ",
      "unlockAll": "Go Gold to Unlock All Stats"
    },
    "info": {
      "hometown": "Hometown: ",
      "editInfo": "Edit info",
      "joinedOn": "Joined on {}",
      "months": {
        "1": "Jan",
        "2": "Feb",
        "3": "Mar",
        "4": "Apr",
        "5": "May",
        "6": "Jun",
        "7": "Jul",
        "8": "Aug",
        "9": "Sep",
        "10": "Oct",
        "11": "Nov",
        "12": "Dec"
      },
      "1stPlace": "1st Place",
      "2ndPlace": "2nd Place",
      "3rdPlace": "3rd Place",
      "totalGames": "Total Games",
      "asOfMay": "as of May 2023",
      "style": "Style",
      "achievements": "Achievements",
      "color": "Color",
      "details": "Details"
    },
    "otp": {
      "title": "Current email verification",
      "description": "Please enter the code sent to your current email"
    },
    "errors": {
      "updateFailed": "Failed to update",
      "nameProfanity": "Name cannot have profanities",
      "nameTaken": "Name is already taken",
      "nameEmpty": "Name cannot be empty",
      "statusProfanity": "Status cannot have profanities",
      "descriptionProfanity": "Description cannot have profanities",
      "cityProfanity": "City cannot have profanities"
    }
  },
  "auth": {
    "fb": {
      "newPassword": "New password",
      "newPasswordHint": "Enter your new password",
      "verifiedTitle": "Verified",
      "verifiedMsg": "You email has been successfully verified.",
      "passResetMsg": "Your password email has been successfully changed.",
      "expired": "Invalid or expired link, try to verify email again.",
      "weakPass": "Password too weak, try again.",
      "expiredPassReset": "Invalid or expired link, try to reset your password again.",
      "emailChangedTitle": "Email changed",
      "emailChangedMsg": "Your email has been successfully changed. You need to login again.",
      "recoveredEmailTitle": "Email recovered",
      "recoveredEmailMsg": "Your email has been successfully recovered."
    },
    "linking": {
      "title": "Account Linking",
      "message": "Logging in with $newProvider will override your existing logins. Continue?",
      "no": "No",
      "yes": "Yes"
    },
    "footer": {
      "agree": "By tapping a sign in button, you agree to the\n",
      "tos": "Terms of Service",
      "and": " and ",
      "privacy": "Privacy Policy"
    },
    "code": {
      "msg": "Enter the code sent to {}",
      "confirm": "Confirm",
      "sent": "Email sent",
      "sentMsg": "A new code has been sent to {}",
      "resend": "Resend Code",
      "continueWithEmail": "Have a password? Continue here"
    },
    "email": {
      "label": "Enter your email to sign up or login into Landover",
      "button": "Confirm"
    },
    "signUp": {
      "nickname": {
        "label": "Nickname",
        "placeholder": "Enter Nickname...",
        "empty": "Please enter a nickname",
        "short": "Please enter a nickname of at least 3 characters",
        "profanity": "Profanity detected. Try again."
      },
      "password": {
        "label": "Confirm Password",
        "placeholder": "Confirm Password...",
        "empty": "Please enter a password",
        "mismatch": "Passwords do not match"
      }
    },
    "verify": {
      "email": "Verify your email",
      "message": "A verification email has been sent to you! Please check your mailbox to verify the account before you sign in",
      "resend": "Resend"
    },
    "login": "Log In",
    "useFB": "Continue with Facebook",
    "useGoogle": "Continue with Google",
    "useEmail": "Continue with Email",
    "useApple": "Continue with Apple",
    "or": "OR",
    "passRequired": "Your password is required",
    "enterPassword": "Please enter your password for {}"
  },
  "alerts": {
    "ok": "OK",
    "cancel": "Cancel"
  },
  "forms": {
    "submit": "Submit",
    "nicknameEmpty": "Please enter a nickname",
    "nicknameShort": "Please enter a nickname of at least 3 characters",
    "email": "Email",
    "emailEmpty": "Please enter an email",
    "emailPlaceholder": "Enter Email...",
    "emailInvalid": "Please enter a valid email address",
    "password": "Password",
    "passwordPlaceholder": "Enter Password...",
    "passwordEmpty": "Please enter a password",
    "forgotPassword": "Forgot Password?",
    "resetPasswordTitle": "Reset Password",
    "resetPasswordEmail": "Enter your email",
    "resetPasswordEmailSent": "Email sent",
    "resetPasswordEmailSentMsg": "Please check your inbox"
  },
  "codeJoin": {
    "join": "Join"
  },
  "history": {
    "title": "HISTORY",
    "notAvailable": "Old game results are unavailable.",
    "turns": "{} Turns",
    "players": "{} players",
    "noHistory": "No Match History"
  },
  "settings": {
    "title": "SETTINGS",
    "editInfo": "Edit info",
    "stats": "Stats",
    "themes": "Themes & Colors",
    "history": "History",
    "logout": {
      "title": "Log Out",
      "guest": {
        "title": "Warning!",
        "message": "You are about to logout of your guest account. All data will be lost and all your games will be forfeited. To avoid this, first authenticate your account with another login. Continue?",
        "delete": "Delete Account",
        "cancel": "Cancel"
      }
    },
    "privacy": "Privacy Policy",
    "terms": "Terms of Service"
  },
  "invite": {
    "play": "Play",
    "cancel": "Cancel",
    "inviteFrom": "Invite from {}!"
  },
  "matchmaking": {
    "title": "NEW RANKED GAME",
    "daily": "Start Daily Game",
    "live": "Start Live Game",
    "customGame": {
      "question": "Want to choose your map and settings? ",
      "link": "Create a custom game."
    },
    "dailyDescription":"24 hours to make your move.\n Unlimited games!",
    "liveDescription": "90 seconds to make your move.\n1 game at a time!",
    "gameCreated": "New ranked daily game created.\nYour game will start shortly.",
    "gamesPending": {
      "one": "game pending",
      "other": "games pending"
    }
  },
  "help": {
    "title": "WELCOME TO LANDOVER!",
    "rules": "Rules",
    "video": "Video\nTutorials",
    "tutorial": "Play\nTutorial",
    "discord": "Discord!",
    "questions": "Questions?\n",
    "onboardingText": "For help, you can always go here to replay the tutorial, read rules and watch videos."
  },
  "themes": {
    "title": "Theme & Color",
    "chooseTheme": "Choose Theme",
    "chooseColor": "Choose Color",
    "save": "Save",
    "goGold": "Go Gold to Unlock",
    "selected": "SELECTED"
  },
  "createGame": {
    "options": {
      "title": "OPTIONS",
      "on": "On",
      "off": "Off",
      "time": "Time per Turn",
      "points": "Victory Points",
      "barbDelay": "Barbarians Delay",
      "barbDelayTooltip": "Number of barbarian rolls before\nthe barbarians start to advance\ntowards an attack.",
      "name": "Game Name (optional)",
      "namePlaceholder": "Enter name",
      "public": "Public Game",
      "mapHints": {
        "title": "Map Hints",
        "tooltip": "Enables map hint indicators when building structures."
      },
      "charity": {
        "title": "Charity 7 Rolls",
        "tooltip": "Give one random resource when a 7 is rolled"
      },
      "resources": {
        "title": "Starting Resources",
        "tooltip": "Give every user one resource of every type when a game starts"
      },
      "raids": {
        "title": "Raids",
        "tooltip": "Enable/Disable spending one military to raid your opponent."
      },
      "fairDice": {
        "title": "Fair Dice",
        "tooltip": "Replaces true random with an even\ndistribution of dice rolls."
      },
      "culture": {
        "title": "Culture",
        "tooltip": "Enables Science, Politics, and Commerce\nupgrades so you can collect dev cards\nand earn metros."
      },
      "luckyRaid": {
        "title": "Lucky 7 Raid",
        "tooltip": "Player in last place who rolls a 7\nis rewarded with a free raid."
      }
    },
    "map": {
      "title": "SELECT MAP",
      "maps": "MAPS",
      "favorites": "Favorites",
      "lastPlayed": "Last Played",
      "moreSlots": "Subscribe for more slots",
      "giant": "Giant",
      "normal": "Normal",
      "mapType": "Choose map type",
      "mapTypeMsg": "Choose the type of map you want to create.",
      "createMap": "Create New Map",
      "register": "Register",
      "createAccount": "Create Account",
      "createAccountMsg": "You must register an account to create maps.",
      "search": "Search maps",
      "mapName": "Name",
      "gamesPlayed": "# of games",
      "createdOn": "Created on",
      "noUserMaps": "You have not created any maps",
      "noMaps": "No maps found",
      "noRecentGames": "You have no recent games",
      "noFavorites": "You have no favorite maps",
      "tabs": {
        "standard": "STANDARD",
        "myMaps": "MY MAPS",
        "favorites": "FAVORITES",
        "all": "ALL"
      },
      "adminControls": {
        "confirmDialog": {
          "yes": "Yes",
          "no": "No",
          "confirm": "Confirm",
          "duplicate": "Are you sure you want to duplicate this map?",
          "makeOfficial": "Are you sure you want to make this map official?",
          "deleteFromOfficial": "Are you sure you want to delete this map from official maps?"
        }
      },
      "sort": {
        "newest": "Newest",
        "oldest": "Oldest",
        "mostGames": "Most Games",
        "leastGames": "Least Games",
        "alphabetical": "Alphabetical",
        "reverseAlphabetical": "Alphabetical Desc",
        "popular": "Popular"
      },
      "preview": {
        "selectMap": "Select Map",
        "deleteMap": "Delete Map",
        "editMap": "Edit Map"
      },
      "userInfo": {
        "createdBy": "Created by"
      }
    },
    "playTutorial": {
      "title": "Play tutorial",
      "message": "As a new player to Landover, you must complete one solo game against the bots before you jump into a public game. Try the tutorial!"
    },
    "createGame": "Create Game"
  },
  "join": {
    "title": "Join Games",
    "gameNotAvailable": "This game is not available, try another one",
    "createGame": "Create Game",
    "joinByCode": "Join by Code",
    "filter": {
      "title": "FILTER",
      "button": "Filter",
      "clear": "Clear",
      "allGames": "All Games",
      "liveGames": "Live Games",
      "dailyGames": "Daily Games",
      "allPoints": "All Points",
      "xPoints": "{} points"
    }
  },
  "lobby": {
    "leave": {
      "title": "Leave Game",
      "message": "Are you sure you want to leave this game?",
      "yes": "Leave"
    },
    "add": {
      "recent": "+ Recent",
      "bot": "+ Add Bot",
      "invite": "+ Invite"
    },
    "boot": {
      "button": "Remove",
      "title": "Are you sure you want to kick "
    },
    "rankedLiveLobby": {
      "title": "LIVE RANKED GAME",
      "lobbyState": {
        "waiting": "Wait... Estimated Time: ",
        "areYouReady": "Are you ready?",
        "starting": "Game is starting",
        "waitingForOther": "Waiting for other players..."
      },
      "readyButton": "Ready",
      "opponent": "Opponent",
      "VS": "VS",
      "randomMap": "Random map",
      "gameData": {
        "winCondition": "Win Condition",
        "startingResources": "Starting Resources",
        "charity": "Charity",
        "fairDice": "Fair Dice",
        "turnTimer": "Turn Timer",
        "on": "On",
        "off": "Off"
      }
    },
    "options": {
      "on": "On",
      "off": "Off",
      "points": "Victory Points",
      "time": "Turn timer",
      "luckyRaid": "Lucky 7 Raid",
      "culture": "Culture",
      "barbDelay": "Barbarians Delay",
      "fairDice": "Fair Dice",
      "raids": "Raids"
    },
    "addBot": {
      "title": "ADD BOT",
      "alreadyAdded": "Already Added",
      "unlockBot": "Unlock Bot",
      "addBot": "Add Bot"
    },
    "getReady": {
      "title": "GET READY!",
      "cancel": "Cancel",
      "ready": "Ready"
    },
    "ranked": {
      "title": "Joined!",
      "message": "You joined a daily game match! You will be notified when game starts."
    },
    "recent": {
      "title": "INVITE PLAYERS",
      "notificationTurnedOf": "This player has turned off invitations from recent players. This player will be removed from your list.",
      "noRecent": "No recent players!"
    },
    "joinPrivate": {
      "joinAnyway": "Join anyway",
      "cancel": "Cancel"
    },
    "gameType": {
      "ranked": "RANKED GAME",
      "quick": "QUICK GAME",
      "tutorial": "TUTORIAL",
      "daily": "DAILY GAME",
      "solo": "SOLO GAME",
      "live": "LIVE GAME"
    },
    "lobbyLabel": "Lobby:",
    "code": "Code: ",
    "join": "JOIN",
    "waiting": "Waiting...",
    "waitingForHost": "Waiting for host...",
    "start": "Start",
    "starting": "Game Starting",
    "startingTutorial": "Starting tutorial",
    "initTutorial": "Initializing tutorial...",
    "creatingNewLobby": "Creating new lobby...",
    "checkingExisting": "Checking existing games...",
    "matchingGameFound": "Matching game found!",
    "loadingLobby": "Loading game lobby...",
    "loadingGame": "Loading game...",
    "joined": "Joined!",
    "alreadyInQueue": "You are already in the queue, you will be notified when a game starts.",
    "lobbyFull": "Lobby full!",
    "hostToAdd": "You must be a host to add a bot",
    "cannotBoot": "You cannot boot this player",
    "notFound": "Lobby not found",
    "waitingForLot": "You are already waiting for a lot of games to start. We’ll notify you when it’s your turn to move.",
    "kicked": "Kicked!",
    "kickedMsg": "The host has removed you from this game. Try joining a different game.",
    "timeOut": "Timed out",
    "timeOutMsg": "You didn't accept the game in time.",
    "rematchCanceled": "Rematch canceled",
    "rematchCanceledMsg": "Someone rejected this game.",
    "gameCanceled": "Game canceled",
    "gameCanceledMsg": "The host has ended this game."
  },
  "builder": {
    "create": {
      "title": "CREATE MAP!",
      "ok": "Ok",
      "firstMap": "Want to create your first custom map?\nUse the map builder to design your very own world!",
      "randomNumber": "Any tiles without a number will be randomly assigned a number each game",
      "mysteryTiles": "A mystery tile that cannot be placed on initially and is only revealed when a player explores it",
      "randomResources": "A randomly assigned land resource at game start"
    },
    "controls": {
      "info": "Information",
      "tiles": "Tiles",
      "harbors": "Harbors"
    },
    "info": {
      "name": {
        "title": "Name",
        "placeholder": "Enter name..."
      },
      "description": {
        "title": "Description",
        "placeholder": "Enter description..."
      },
      "points": "Victory Points"
    },
    "terrain": {
      "nonPlacement": "Non Placement Tile",
      "nonPlacementHint": "Select land tiles that are not allowed initial settlements."
    },
    "unsaved": {
      "title": "Unsaved Changes",
      "message": "You have unsaved changes to this map?",
      "yes": "Exit",
      "no": "Save & Exit"
    },
    "title": "MAP BUILDER",
    "save": "Save",
    "openControls": "Open Controls",
    "profanity": "Profanity detected. Try again.",
    "saved": {
      "title": "Success!",
      "message": "Your map has been saved!"
    },
    "validation": {
      "emptyName": "Please give your map a name.",
      "invalidName": "Please enter a valid map name."
    },
    "list": {
      "by": "By: {}",
      "on": "On: {}",
      "games": "Games: {}",
      "vp": "VP: {}",
      "deleteOfficial": {
        "title": "Delete Action",
        "message": "Official maps are undeletable."
      },
      "delete": {
        "title": "Delete",
        "message": "Are you sure you want to delete this map?",
        "yes": "Delete",
        "no": "Cancel"
      }
    }
  },
  "notifications": {
    "title": "Don't Miss Your Turn!",
    "enable": "Enable Notifications",
    "enableEmail": "Enable Email Notifications",
    "enableText": "Enable notifications and never miss your turn. We'll remind you when it's time to jump back in so you can keep the game moving!",
    "notNow": "Don't enable for now"
  },
  "unsubscribe": {
    "ask": {
      "title": "Are you sure?",
      "message": "Are you sure you want to unsubscribe from game updates emails?",
      "yes": "Unsubscribe"
    },
    "unsubscribed": {
      "title": "Unsubscribed",
      "yes": "Home",
      "message": "You have been successfully unsubscribed. You can turn on game updates emails again in the settings."
    }
  },
  "loading": {
    "title": "PLEASE WAIT"
  },
  "seasons": {
    "leaderboard": {
      "title": "SEASON LEADERBOARD",
      "player": "Player",
      "games": "# Games",
      "SP": "SP (Season Points)",
      "reward": "Reward"
    },
    "noPlayers": "No players yet",
    "unlockAchievement": "Complete 10 games\nto unlock achievement"
  },
  "showcase": {
    "tile1": "The game board is made up of hexagon <bold>tiles</bold>, each one with a <bold>resource</bold> and number.",
    "tile2": "Each turn a player rolls the <bold>dice</bold> and if that number is rolled, anyone with a settlement on that tile will collect the <bold>resource</bold> of that tile. The dice rolled are <bold>2 6-sided dice</bold>, so the best numbers are 6 and 8, then 5 and 9.",
    "cornerValues1": "See those numbers on the <bold>corners</bold> of each <bold>tile</bold>?",
    "cornerValues2": "They are there only during placement to help you easily locate <bold>high value corners</bold>, ones that are adjacent to good tiles! The highest the corner value, the better it is!",
    "resources1": "These are your resource cards!",
    "resources2": "They can be used to build different structures like <bold>roads, villages and cities</bold>.\nAny time you can build, Landover will suggest those options to you on the map.",
    "military1": "This is your <bold>military level</bold>, it's currently 0.\nYou can level up your military by spending <bold>1 Wheat</bold> and <bold>1 Sheep</bold>.",
    "military2": "Military defends against <bold>barbarian attacks</bold> and can be used to <bold>raid</bold> other players.",
    "barbarians1": "This is the barbarian tracker. Each time a <bold>barbarian (skull)</bold> is rolled on the <bold>dice</bold>, the barbarians move one step closer to attacking.",
    "barbarians2": "You'll need to level up your military to avoid <bold>losing a city</bold>.",
    "culture1": "These 3 circles represent your culture levels for <bold>Science</bold> (green), <bold>Commerce</bold> (yellow), and <bold>Politics</bold> (blue).",
    "culture2": "Leveling up your culture will give you <bold>development cards</bold>. Getting to level 3 unlocks a <bold>special ability</bold>. And get to level 4 first to earn a metro worth <bold>2 VPs</bold>.",
    "playerBars1": "These are the player bars.\nThey show an overview of every players cards and levels.",
    "playerBars2": "The top row from left to right is: <bold>Number of ports</bold> (players with 3 or more ports can claim Port Authority for <bold>2 VPs</bold>), <bold>longest route length</bold> (players with the longest route get <bold>2 VPs</bold>), and <bold>Victory Points</bold>.",
    "playerBars3": "The next row shows number of <bold>resource/commodity cards</bold>, number of <bold>dev cards</bold>, followed by their <bold>military</bold> and <bold>culture</bold> levels.\nYou can tap on a player tile to see more info!",
    "victoryPoints": "The objective of Landover is to achieve Victory Points by building settlements and expanding your empire."
  },
  "buildingTypes": {
    "military": "Military",
    "road": "Road",
    "boat": "Bridge",
    "either": "Either",
    "city": "City",
    "cityWall": "City Wall",
    "metro": "Metro",
    "village": "Village"
  }
}